AUTHORS.rst
CHANGES.rst
LICENSE.txt
MANIFEST.in
README.rst
setup.cfg
setup.py
django_password_validation.egg-info/PKG-INFO
django_password_validation.egg-info/SOURCES.txt
django_password_validation.egg-info/dependency_links.txt
django_password_validation.egg-info/not-zip-safe
django_password_validation.egg-info/requires.txt
django_password_validation.egg-info/top_level.txt
password_validation/__init__.py
password_validation/conf.py
password_validation/forms.py
password_validation/validation.py
password_validation/views.py
password_validation/test/__init__.py
password_validation/test/conftest.py
password_validation/test/settings.py
password_validation/test/test_forms.py
password_validation/test/test_settings.py
password_validation/test/test_validators.py
password_validation/test/test_views.py